odoo9_addon_stock_available_mrp-9.0.1.0.0.99.dev24-py3.8-nspkg.pth
odoo_addons/stock_available_mrp/README.rst
odoo_addons/stock_available_mrp/__init__.py
odoo_addons/stock_available_mrp/__openerp__.py
odoo_addons/stock_available_mrp/demo/mrp_bom.yml
odoo_addons/stock_available_mrp/i18n/ca.po
odoo_addons/stock_available_mrp/i18n/de.po
odoo_addons/stock_available_mrp/i18n/el_GR.po
odoo_addons/stock_available_mrp/i18n/es.po
odoo_addons/stock_available_mrp/i18n/es_ES.po
odoo_addons/stock_available_mrp/i18n/es_MX.po
odoo_addons/stock_available_mrp/i18n/eu.po
odoo_addons/stock_available_mrp/i18n/fi.po
odoo_addons/stock_available_mrp/i18n/fr.po
odoo_addons/stock_available_mrp/i18n/fr_CH.po
odoo_addons/stock_available_mrp/i18n/fr_FR.po
odoo_addons/stock_available_mrp/i18n/gl.po
odoo_addons/stock_available_mrp/i18n/hr.po
odoo_addons/stock_available_mrp/i18n/hr_HR.po
odoo_addons/stock_available_mrp/i18n/it.po
odoo_addons/stock_available_mrp/i18n/nl.po
odoo_addons/stock_available_mrp/i18n/nl_NL.po
odoo_addons/stock_available_mrp/i18n/pt.po
odoo_addons/stock_available_mrp/i18n/pt_BR.po
odoo_addons/stock_available_mrp/i18n/ro.po
odoo_addons/stock_available_mrp/i18n/ru.po
odoo_addons/stock_available_mrp/i18n/sk.po
odoo_addons/stock_available_mrp/i18n/sl.po
odoo_addons/stock_available_mrp/i18n/stock_available_mrp.pot
odoo_addons/stock_available_mrp/i18n/tr.po
odoo_addons/stock_available_mrp/i18n/tr_TR.po
odoo_addons/stock_available_mrp/i18n/vi_VN.po
odoo_addons/stock_available_mrp/i18n/zh_CN.po
odoo_addons/stock_available_mrp/models/__init__.py
odoo_addons/stock_available_mrp/models/product_product.py
odoo_addons/stock_available_mrp/models/product_template.py
odoo_addons/stock_available_mrp/static/description/icon.png
odoo_addons/stock_available_mrp/tests/__init__.py
odoo_addons/stock_available_mrp/tests/test_potential_qty.py
odoo9_addon_stock_available_mrp-9.0.1.0.0.99.dev24.dist-info/METADATA
odoo9_addon_stock_available_mrp-9.0.1.0.0.99.dev24.dist-info/WHEEL
odoo9_addon_stock_available_mrp-9.0.1.0.0.99.dev24.dist-info/namespace_packages.txt
odoo9_addon_stock_available_mrp-9.0.1.0.0.99.dev24.dist-info/top_level.txt
odoo9_addon_stock_available_mrp-9.0.1.0.0.99.dev24.dist-info/RECORD
